patronum/__init__.py
patronum-0.0.0.dev1.dist-info/METADATA
patronum-0.0.0.dev1.dist-info/WHEEL
patronum-0.0.0.dev1.dist-info/licenses/LICENSE
patronum-0.0.0.dev1.dist-info/RECORD
