Metadata-Version: 2.4
Name: patronum
Version: 0.0.0.dev1
Summary: A Spring Boot-inspired Dependency Injection and Configuration Framework for Python.
Project-URL: Homepage, https://github.com/patronum-project/patronum
Project-URL: Repository, https://github.com/patronum-project/patronum
Project-URL: Issues, https://github.com/patronum-project/patronum/issues
Author-email: Kordian Grabowski <kordiangrabowski@gmail.com>
License: MIT License
License-File: LICENSE
Keywords: configuration,dependency injection,di,framework,ioc,python,service discovery,spring
Classifier: Development Status :: 2 - Pre-Alpha
Classifier: Intended Audience :: Developers
Classifier: License :: OSI Approved :: MIT License
Classifier: Operating System :: OS Independent
Classifier: Programming Language :: Python :: 3
Classifier: Programming Language :: Python :: 3.13
Classifier: Topic :: Software Development :: Libraries :: Application Frameworks
Classifier: Topic :: Software Development :: Libraries :: Python Modules
Classifier: Typing :: Typed
Requires-Python: >=3.13
Requires-Dist: pydantic>=2.0
Requires-Dist: pyyaml>=6.0
Provides-Extra: dev
Requires-Dist: pytest-cov>=6.0; extra == 'dev'
Requires-Dist: pytest>=8.0; extra == 'dev'
Requires-Dist: ruff>=0.11.0; extra == 'dev'
